{
    "name": "Pastel Dream",
    "description": "Soft muted pastels with dusty blues and mauves - dreamy artistic aesthetic",
    "bg": "#FAF7F2",
    "text": "#5D5A6D",
    "gradient_color": "#FAF7F2",
    "water": "#D4E4ED",
    "parks": "#E8EDE4",
    "forest": "#D8E8D8",
    "buildings": "#EDE8EC",
    "road_motorway": "#7B8794",
    "road_primary": "#9BA4B0",
    "road_secondary": "#B5AEBB",
    "road_tertiary": "#C9C0C9",
    "road_residential": "#D8D2D8",
    "road_default": "#C9C0C9",
    "railway": "#7B8794",
    "railway_dash": "#FAF7F2",
    "cycle_route": "#A8B8A8",
    "admin_boundary": "#C9C0C9",
    "historic": "#9B8FA8",
    "poi": "#9B7AA8"
}
